{
    "configurations": [
        {
            "name": "Linux",
            "includePath": [
                "${workspaceFolder}",
                "/usr/local/include",
                "/usr/include",
                "${workspaceFolder}/include",
                "../shared/include"
            ],
            "defines": [
                "_GNU_SOURCE"
            ],
            "intelliSenseMode": "clang-x64",
            "browse": {
                "path": [
                    "${workspaceFolder}",
                    "${workspaceFolder}/include",
                    "../shared/include",
                    "/usr/local/include",
                    "/usr/include"
                ],
                "limitSymbolsToIncludedHeaders": true,
                "databaseFilename": ""
            },
            "compilerPath": "/usr/bin/gcc",
            "cStandard": "c11",
            "cppStandard": "c++17"
        }
    ],
    "version": 4
}